af_practical_astronomy/__init__.py
af_practical_astronomy/coordinate_functions.py
af_practical_astronomy/time_functions.py
af_practical_astronomy/utils.py
af_practical_astronomy-1.0.8.dist-info/LICENSE
af_practical_astronomy-1.0.8.dist-info/METADATA
af_practical_astronomy-1.0.8.dist-info/WHEEL
af_practical_astronomy-1.0.8.dist-info/top_level.txt
af_practical_astronomy-1.0.8.dist-info/RECORD
