Metadata-Version: 2.1
Name: af_practical_astronomy
Version: 1.0.8
Summary: A practical astronomy library
Home-page: https://github.com/yourusername/practical_astronomy
Author: Artur Foden
Classifier: Programming Language :: Python :: 3
License-File: LICENSE
Requires-Dist: astronomy-types
